newrl/__init__.py
newrl/hash.py
newrl/node.py
newrl/signer.py
newrl/wallet.py
newrl-0.2.9.dist-info/LICENSE
newrl-0.2.9.dist-info/METADATA
newrl-0.2.9.dist-info/WHEEL
newrl-0.2.9.dist-info/top_level.txt
newrl-0.2.9.dist-info/RECORD
