Metadata-Version: 2.1
Name: newrl
Version: 0.2.9
Summary: Python SDK for Newrl blockchain
Home-page: https://github.com/asqi/newrl
Author: Kousthub Raja
Author-email: kousthub@asqi.in
License: MIT
Download-URL: https://github.com/asqisys/newrl-py/archive/refs/tags/v_02.tar.gz
Project-URL: Bug Tracker, https://github.com/asqisys/newrl-py/issues
Keywords: newrl,blockchain,client
Platform: UNKNOWN
Classifier: Development Status :: 3 - Alpha
Classifier: Intended Audience :: Developers
Classifier: Topic :: Software Development :: Build Tools
Classifier: License :: OSI Approved :: MIT License
Classifier: Programming Language :: Python :: 3
Classifier: Programming Language :: Python :: 3.4
Classifier: Programming Language :: Python :: 3.5
Classifier: Programming Language :: Python :: 3.6
Requires-Python: >=3.6
License-File: LICENSE
Requires-Dist: requests
Requires-Dist: ecdsa
Requires-Dist: pycryptodome
